nexium_exchanger/__init__.py
nexium_exchanger/api_client.py
nexium_exchanger/api_response.py
nexium_exchanger/configuration.py
nexium_exchanger/exceptions.py
nexium_exchanger/py.typed
nexium_exchanger/rest.py
nexium_exchanger/api/__init__.py
nexium_exchanger/api/auth_entities_api.py
nexium_exchanger/api/currencies_api.py
nexium_exchanger/api/customers_api.py
nexium_exchanger/api/employee_payment_methods_api.py
nexium_exchanger/api/employees_api.py
nexium_exchanger/api/exchange_directions_api.py
nexium_exchanger/api/exchange_rates_api.py
nexium_exchanger/api/exchangers_api.py
nexium_exchanger/api/incoming_payment_requests_api.py
nexium_exchanger/api/kyc_api.py
nexium_exchanger/api/orders_api.py
nexium_exchanger/api/outgoing_payment_requests_api.py
nexium_exchanger/api/payment_methods_api.py
nexium_exchanger/api/payment_requisites_api.py
nexium_exchanger/api/payments_api.py
nexium_exchanger/api/tags_api.py
nexium_exchanger/api/variables_api.py
nexium_exchanger/api/wallet_operations_api.py
nexium_exchanger/api/wallets_api.py
nexium_exchanger/models/__init__.py
nexium_exchanger/models/auth_entity_response.py
nexium_exchanger/models/auth_entity_short_out.py
nexium_exchanger/models/currency_create.py
nexium_exchanger/models/currency_out.py
nexium_exchanger/models/currency_update.py
nexium_exchanger/models/customer_base_out_input.py
nexium_exchanger/models/customer_base_out_output.py
nexium_exchanger/models/customer_coupon_create.py
nexium_exchanger/models/customer_coupon_out.py
nexium_exchanger/models/customer_coupon_type_enum.py
nexium_exchanger/models/customer_create.py
nexium_exchanger/models/customer_detail_out_input.py
nexium_exchanger/models/customer_detail_out_output.py
nexium_exchanger/models/customer_id_out.py
nexium_exchanger/models/customer_invite_detail_out_input.py
nexium_exchanger/models/customer_invite_detail_out_output.py
nexium_exchanger/models/customer_invite_summary.py
nexium_exchanger/models/customer_list_out_input.py
nexium_exchanger-0.1.7.dist-info/METADATA
nexium_exchanger-0.1.7.dist-info/WHEEL
nexium_exchanger-0.1.7.dist-info/top_level.txt
nexium_exchanger-0.1.7.dist-info/RECORD
